.gitignore
LICENSE.txt
Makefile
README.md
setup.py
src/progress_executor/__init__.py
src/progress_executor/main.py
src/progress_executor/pool_progress_executor.py
src/progress_executor/progress_executor_base.py
src/progress_executor/sync_progress_executor.py
src/progress_executor.egg-info/PKG-INFO
src/progress_executor.egg-info/SOURCES.txt
src/progress_executor.egg-info/dependency_links.txt
src/progress_executor.egg-info/entry_points.txt
src/progress_executor.egg-info/requires.txt
src/progress_executor.egg-info/top_level.txt
tests/basic_run.py