Metadata-Version: 2.1
Name: progress-executor
Version: 0.2
Summary: Subclasses of concurrent.future.Executor that correctly handle cancelling and progress
Home-page: https://github.com/JulienBrn/progress_executor
Download-URL: https://github.com/JulienBrn/progress_executor.git
Author: Julien Braine
Author-email: julienbraine@yahoo.fr
License: MIT
Keywords: python
Requires-Python: >=3.11
License-File: LICENSE.txt
